otai_hf_local/__init__.py
otai_hf_local/hf_classification_service.py
otai_hf_local/hf_local_plugin.py
otai_hf_local-1.5.14.dist-info/METADATA
otai_hf_local-1.5.14.dist-info/WHEEL
otai_hf_local-1.5.14.dist-info/entry_points.txt
otai_hf_local-1.5.14.dist-info/top_level.txt
otai_hf_local-1.5.14.dist-info/RECORD
